langchain_aerospike/__init__.py
langchain_aerospike/vectorstores/__init__.py
langchain_aerospike/vectorstores/aerospike.py
langchain_aerospike-0.1.0.dist-info/LICENSE
langchain_aerospike-0.1.0.dist-info/METADATA
langchain_aerospike-0.1.0.dist-info/WHEEL
langchain_aerospike-0.1.0.dist-info/entry_points.txt
langchain_aerospike-0.1.0.dist-info/RECORD
