Metadata-Version: 2.3
Name: langchain-aerospike
Version: 0.1.0
Summary: LangChain integration for Aerospike Vector Store
License: MIT
Author: Aerospike Integrations
Author-email: info@aerospike.com
Requires-Python: >=3.9,<4.0
Classifier: Development Status :: 4 - Beta
Classifier: Intended Audience :: Developers
Classifier: License :: OSI Approved :: MIT License
Classifier: Programming Language :: Python :: 3
Classifier: Programming Language :: Python :: 3.9
Classifier: Programming Language :: Python :: 3.10
Classifier: Programming Language :: Python :: 3.11
Classifier: Programming Language :: Python :: 3.12
Classifier: Programming Language :: Python :: 3.13
Requires-Dist: aerospike-vector-search (>=4.1.0)
Requires-Dist: langchain-core (>=0.1.0)
Requires-Dist: numpy (>=1.20.0)
Project-URL: Documentation, https://github.com/aerospike/langchain-aerospike
Project-URL: Repository, https://github.com/aerospike/langchain-aerospike
